{"electricity_department": [{"name": "sanket", "mobile": "9876543210", "address": "sangamner", "description": "light problem", "date": "2021-06-15", "image_path": "data/complaint_images/1623730612.3317344.jpg", "class": "electricity_department"}, {"name": "akshay", "mobile": "9146405749", "address": "sangamner", "description": "electricity problem", "date": "2021-06-15", "image_path": "data/complaint_images/1623730698.1522295.jpg", "class": "electricity_department"}], "garbage_department": [{"name": "Akshay", "mobile": "9146405749", "address": "sangamner", "description": "garbage management problem", "date": "2021-06-15", "image_path": "data/complaint_images/1623729828.000096.jpg", "class": "garbage_department"}, {"name": "sanket", "mobile": "9146405749", "address": "sangamner", "description": "garbage problem", "date": "2021-06-15", "image_path": "data/complaint_images/1623729903.5578184.jpg", "class": "garbage_department"}, {"name": "shital", "mobile": "8976542310", "address": "sangamner", "description": "garbage", "date": "2021-06-15", "image_path": "data/complaint_images/1623730050.340534.jpg", "class": "garbage_department"}, {"name": "akshay", "mobile": "9146405749", "address": "nimgaon bk", "description": "garbage", "date": "2021-06-15", "image_path": "data/complaint_images/1623730086.4203112.jpg", "class": "garbage_department"}, {"name": "shubhangi", "mobile": "9856431269", "address": "sangamner", "description": "garbage", "date": "2021-06-15", "image_path": "data/complaint_images/1623730174.8850005.jpg", "class": "garbage_department"}], "street_department": [{"name": "Akshay Kanawade", "mobile": "9146405749", "address": "sangamner", "description": "road damage", "date": "2021-06-15", "image_path": "data/complaint_images/1623730254.2556472.jpg", "class": "street_department"}, {"name": "shital", "mobile": "9874245677", "address": "sangamner", "description": "road problem", "date": "2021-06-15", "image_path": "data/complaint_images/1623730357.0643115.jpg", "class": "street_department"}, {"name": "shubhangi", "mobile": "9888664323", "address": "sangamner", "description": "road damage", "date": "2021-06-15", "image_path": "data/complaint_images/1623730418.9169157.jpg", "class": "street_department"}, {"name": "sanket", "mobile": "9767655632", "address": "sangamner", "description": "road problem", "date": "2021-06-15", "image_path": "data/complaint_images/1623730481.308549.jpg", "class": "street_department"}]}